ModelProgrammer/ChatBot.py
ModelProgrammer/ChatUI.py
ModelProgrammer/CodeSummarizer.py
ModelProgrammer/Conversation.py
ModelProgrammer/ConversationDB.py
ModelProgrammer/Programmer.py
ModelProgrammer/Terminal.py
ModelProgrammer/TokenCounter.py
ModelProgrammer/__init__.py
ModelProgrammer-0.0.3.dist-info/LICENSE
ModelProgrammer-0.0.3.dist-info/METADATA
ModelProgrammer-0.0.3.dist-info/WHEEL
ModelProgrammer-0.0.3.dist-info/top_level.txt
ModelProgrammer-0.0.3.dist-info/RECORD
