Metadata-Version: 2.1
Name: ModelProgrammer
Version: 0.0.3
Summary: An experiment in AI terminal interaction.
Home-page: https://github.com/inventor2525/ModelProgrammer
Author: Charlie Angela Mehlenbeck
Author-email: charlie_inventor2003@yahoo.com
Requires-Python: >=3.10
License-File: LICENSE
Requires-Dist: tiktoken
Requires-Dist: PyQt5
Requires-Dist: openai
